SchemathesisLibrary/__init__.py
SchemathesisLibrary/schemathesisreader.py
robotframework_schemathesislibrary-1.2.0.dist-info/licenses/LICENSE
robotframework_schemathesislibrary-1.2.0.dist-info/METADATA
robotframework_schemathesislibrary-1.2.0.dist-info/WHEEL
robotframework_schemathesislibrary-1.2.0.dist-info/top_level.txt
robotframework_schemathesislibrary-1.2.0.dist-info/RECORD
