Metadata-Version: 2.4
Name: robotframework-schemathesislibrary
Version: 1.2.0
Summary: Robot Framework SchemathesisLibrary to automatically create test cases from API specifications.
Author-email: Tatu Aalto <aalto.tatu@gmail.com>
License-Expression: Apache-2.0
Keywords: Robot Framework,Schemathesis,API Testing,Test Automation
Requires-Python: >=3.10.1
License-File: LICENSE
Requires-Dist: robotframework>=7.2.2
Requires-Dist: robotframework-datadriver>=1.11.2
Requires-Dist: robotframework-pythonlibcore>=4.4.1
Requires-Dist: schemathesis>=4.7.0
Dynamic: license-file
